MANIFEST.in
README.md
pyproject.toml
setup.py
Pyxides/__init__.py
Pyxides/cal.py
Pyxides/gce.py
Pyxides/imager.py
Pyxides/lsm.py
Pyxides/mqt.py
Pyxides/ms.py
Pyxides/std.py
Pyxides/im/__init__.py
Pyxides/im/argo.py
Pyxides/im/casa.py
Pyxides/im/lwimager.py
Pyxides/im/moresane.py
Pyxides/im/wsclean.py
Pyxides/utils/__init__.py
Pyxides/utils/casa_scripts.py
Pyxis/Commands.py
Pyxis/Internals.py
Pyxis/ModSupport.py
Pyxis/__init__.py
Pyxis/bin/ipyxis
Pyxis/bin/pyxis
Pyxis/recipes/imagers-test/WSRT_makems.cfg
Pyxis/recipes/imagers-test/basic_imager_test.py
Pyxis/recipes/imagers-test/imager.conf
Pyxis/recipes/imagers-test/WSRT_ANTENNA/table.dat
Pyxis/recipes/imagers-test/WSRT_ANTENNA/table.f0
Pyxis/recipes/imagers-test/WSRT_ANTENNA/table.info
Pyxis/recipes/imagers-test/WSRT_ANTENNA/table.lock
Pyxis/recipes/meqtrees-batch-test/WSRT_makems.cfg
Pyxis/recipes/meqtrees-batch-test/batch_test.py
Pyxis/recipes/meqtrees-batch-test/cal.py
Pyxis/recipes/meqtrees-batch-test/imager.conf
Pyxis/recipes/meqtrees-batch-test/sim.py
Pyxis/recipes/meqtrees-batch-test/test-lsm.txt
Pyxis/recipes/meqtrees-batch-test/test-lsm1.txt.reference
Pyxis/recipes/meqtrees-batch-test/test-lsm2.txt.reference
Pyxis/recipes/meqtrees-batch-test/test-refimage.fits
Pyxis/recipes/meqtrees-batch-test/test-refresidual.fits
Pyxis/recipes/meqtrees-batch-test/testing.tdl.conf
Pyxis/recipes/meqtrees-batch-test/WSRT_ANTENNA/table.dat
Pyxis/recipes/meqtrees-batch-test/WSRT_ANTENNA/table.f0
Pyxis/recipes/meqtrees-batch-test/WSRT_ANTENNA/table.info
Pyxis/recipes/meqtrees-batch-test/WSRT_ANTENNA/table.lock
astro_pyxis.egg-info/PKG-INFO
astro_pyxis.egg-info/SOURCES.txt
astro_pyxis.egg-info/dependency_links.txt
astro_pyxis.egg-info/requires.txt
astro_pyxis.egg-info/top_level.txt
astro_pyxis.egg-info/zip-safe